underground/__init__.py
underground/feed.py
underground/metadata.py
underground/models.py
underground/version
underground/cli/__init__.py
underground/cli/__main__.py
underground/cli/cli.py
underground/cli/feed.py
underground/cli/findstops.py
underground/cli/stops.py
underground/cli/version.py
underground-2.0.0.data/data/readme.md
underground-2.0.0.dist-info/METADATA
underground-2.0.0.dist-info/WHEEL
underground-2.0.0.dist-info/entry_points.txt
underground-2.0.0.dist-info/top_level.txt
underground-2.0.0.dist-info/RECORD
