Metadata-Version: 2.4
Name: underground
Version: 2.0.0
Summary: Utilities for NYC's realtime MTA data feeds.
Home-page: https://github.com/nolanbconaway/underground
Author: Nolan Conaway
Author-email: nolanbconaway@gmail.com
License: MIT
Keywords: nyc,transit,subway,command-line,cli
Classifier: Programming Language :: Python :: 3.9
Classifier: Programming Language :: Python :: 3.10
Classifier: Programming Language :: Python :: 3.11
Classifier: Programming Language :: Python :: 3.12
Classifier: Programming Language :: Python :: 3.13
Classifier: Programming Language :: Python :: 3.14
Requires-Dist: requests==2.*
Requires-Dist: google~=2.0
Requires-Dist: gtfs-realtime-bindings==0.0.6
Requires-Dist: protobuf<=3.20.3,>=3.19.6
Requires-Dist: protobuf3-to-dict==0.1.*
Requires-Dist: click<9,>=7
Requires-Dist: pydantic==2.*
Provides-Extra: dev
Requires-Dist: pytest==8.*; extra == "dev"
Requires-Dist: ruff==0.14.*; extra == "dev"
Requires-Dist: requests-mock==1.*; extra == "dev"
Dynamic: author
Dynamic: author-email
Dynamic: classifier
Dynamic: description
Dynamic: description-content-type
Dynamic: home-page
Dynamic: keywords
Dynamic: license
Dynamic: provides-extra
Dynamic: requires-dist
Dynamic: summary
